{"container_type": "Author", "filled": ["basics", "publications", "indices", "counts"], "scholar_id": "xf1FSRYAAAAJ", "source": "AUTHOR_PROFILE_PAGE", "name": "Lishen Qu", "url_picture": "https://scholar.googleusercontent.com/citations?view_op=view_photo&user=xf1FSRYAAAAJ&citpid=1", "affiliation": "Nankai University", "organization": 16832670968312042075, "interests": ["Computer Vision"], "email_domain": "@mail.nankai.edu.cn", "homepage": "http://www.qulishen.top/", "citedby": 216, "publications": {"xf1FSRYAAAAJ:WC9gN4BGCRcC": {"container_type": "Publication", "source": "AUTHOR_PUBLICATION_ENTRY", "bib": {"title": "Seeing the unseen: A frequency prompt guided transformer for image restoration", "pub_year": "2024", "citation": "European Conference on Computer Vision, 246-264, 2024"}, "filled": false, "author_pub_id": "xf1FSRYAAAAJ:WC9gN4BGCRcC", "num_citations": 61, "citedby_url": "https://scholar.google.com/scholar?oi=bibs&hl=en&cites=10847674803049857889", "cites_id": ["10847674803049857889"]}, "xf1FSRYAAAAJ:QyXJ3EUuO1IC": {"container_type": "Publication", "source": "AUTHOR_PUBLICATION_ENTRY", "bib": {"title": "NTIRE 2026 The 3rd Restore Any Image Model (RAIM) Challenge: Professional Image Quality Assessment (Track 1)", "pub_year": "2026", "citation": "Proceedings of the IEEE/CVF Conference on Computer Vision and Pattern …, 2026"}, "filled": false, "author_pub_id": "xf1FSRYAAAAJ:QyXJ3EUuO1IC", "num_citations": 41, "citedby_url": "https://scholar.google.com/scholar?oi=bibs&hl=en&cites=12393241805707266925", "cites_id": ["12393241805707266925"]}, "xf1FSRYAAAAJ:HGTzPopzzJcC": {"container_type": "Publication", "source": "AUTHOR_PUBLICATION_ENTRY", "bib": {"title": "NTIRE 2026 The 3rd Restore Any Image Model (RAIM) Challenge: AI Flash Portrait (Track 3)", "pub_year": "2026", "citation": "Proceedings of the IEEE/CVF Conference on Computer Vision and Pattern …, 2026"}, "filled": false, "author_pub_id": "xf1FSRYAAAAJ:HGTzPopzzJcC", "num_citations": 38, "citedby_url": "https://scholar.google.com/scholar?oi=bibs&hl=en&cites=5955182691087908596", "cites_id": ["5955182691087908596"]}, "xf1FSRYAAAAJ:OBSaB-F7qqsC": {"container_type": "Publication", "source": "AUTHOR_PUBLICATION_ENTRY", "bib": {"title": "NTIRE 2026 The 3rd Restore Any Image Model (RAIM) Challenge: Multi-Exposure Image Fusion in Dynamic Scenes (Track2)", "pub_year": "2026", "citation": "Proceedings of the IEEE/CVF Conference on Computer Vision and Pattern …, 2026"}, "filled": false, "author_pub_id": "xf1FSRYAAAAJ:OBSaB-F7qqsC", "num_citations": 37, "citedby_url": "https://scholar.google.com/scholar?oi=bibs&hl=en&cites=8352102508845696492", "cites_id": ["8352102508845696492"]}, "xf1FSRYAAAAJ:rHJHxKgnXwkC": {"container_type": "Publication", "source": "AUTHOR_PUBLICATION_ENTRY", "bib": {"title": "A polarization-aided transformer for image deblurring via motion vector decomposition", "pub_year": "2025", "citation": "Proceedings of the Computer Vision and Pattern Recognition Conference, 28061 …, 2025"}, "filled": false, "author_pub_id": "xf1FSRYAAAAJ:rHJHxKgnXwkC", "num_citations": 14, "citedby_url": "https://scholar.google.com/scholar?oi=bibs&hl=en&cites=7017644357288262331", "cites_id": ["7017644357288262331"]}, "xf1FSRYAAAAJ:Dem6FJhTUoYC": {"container_type": "Publication", "source": "AUTHOR_PUBLICATION_ENTRY", "bib": {"title": "AIM 2025 challenge on robust offline video super-resolution: Dataset, methods and results", "pub_year": "2025", "citation": "Proceedings of the IEEE/CVF International Conference on Computer Vision …, 2025"}, "filled": false, "author_pub_id": "xf1FSRYAAAAJ:Dem6FJhTUoYC", "num_citations": 8, "citedby_url": "https://scholar.google.com/scholar?oi=bibs&hl=en&cites=5531347049493478556", "cites_id": ["5531347049493478556"]}, "xf1FSRYAAAAJ:CdxZDUztZiMC": {"container_type": "Publication", "source": "AUTHOR_PUBLICATION_ENTRY", "bib": {"title": "Harmonizing light and darkness: A symphony of prior-guided data synthesis and adaptive focus for nighttime flare removal", "pub_year": "2024", "citation": "arXiv preprint arXiv:2404.00313, 2024"}, "filled": false, "author_pub_id": "xf1FSRYAAAAJ:CdxZDUztZiMC", "num_citations": 6, "citedby_url": "https://scholar.google.com/scholar?oi=bibs&hl=en&cites=18274904117680494235", "cites_id": ["18274904117680494235"]}, "xf1FSRYAAAAJ:-7ulzOJl1JYC": {"container_type": "Publication", "source": "AUTHOR_PUBLICATION_ENTRY", "bib": {"title": "Burstdeflicker: A benchmark dataset for flicker removal in dynamic scenes", "pub_year": "2026", "citation": "Advances in Neural Information Processing Systems 38, 2026"}, "filled": false, "author_pub_id": "xf1FSRYAAAAJ:-7ulzOJl1JYC", "num_citations": 5, "citedby_url": "https://scholar.google.com/scholar?oi=bibs&hl=en&cites=16483814855955249501", "cites_id": ["16483814855955249501"]}, "xf1FSRYAAAAJ:MAUkC_7iAq8C": {"container_type": "Publication", "source": "AUTHOR_PUBLICATION_ENTRY", "bib": {"title": "It takes two: A duet of periodicity and directionality for burst flicker removal", "pub_year": "2026", "citation": "Proceedings of the IEEE/CVF Conference on Computer Vision and Pattern …, 2026"}, "filled": false, "author_pub_id": "xf1FSRYAAAAJ:MAUkC_7iAq8C", "num_citations": 3, "citedby_url": "https://scholar.google.com/scholar?oi=bibs&hl=en&cites=394608980591992764", "cites_id": ["394608980591992764"]}, "xf1FSRYAAAAJ:PyEswDtIyv0C": {"container_type": "Publication", "source": "AUTHOR_PUBLICATION_ENTRY", "bib": {"title": "There and Back Again: A Flexible-Frame Transformer for Multi-Exposure Fusion", "pub_year": "2026", "citation": "arXiv preprint arXiv:2606.27905, 2026"}, "filled": false, "author_pub_id": "xf1FSRYAAAAJ:PyEswDtIyv0C", "num_citations": 1, "citedby_url": "https://scholar.google.com/scholar?oi=bibs&hl=en&cites=8340541772268516102", "cites_id": ["8340541772268516102"]}, "xf1FSRYAAAAJ:jE2MZjpN3IcC": {"container_type": "Publication", "source": "AUTHOR_PUBLICATION_ENTRY", "bib": {"title": "Flarex: A physics-informed dataset for lens flare removal via 2d synthesis and 3d rendering", "pub_year": "2026", "citation": "Advances in Neural Information Processing Systems 38, 2026"}, "filled": false, "author_pub_id": "xf1FSRYAAAAJ:jE2MZjpN3IcC", "num_citations": 1, "citedby_url": "https://scholar.google.com/scholar?oi=bibs&hl=en&cites=17777749941575283345", "cites_id": ["17777749941575283345"]}, "xf1FSRYAAAAJ:DBa1UEJaJKAC": {"container_type": "Publication", "source": "AUTHOR_PUBLICATION_ENTRY", "bib": {"title": "AIM 2025 Challenge on High FPS Motion Deblurring: Methods and Results", "pub_year": "2025", "citation": "Proceedings of the IEEE/CVF International Conference on Computer Vision …, 2025"}, "filled": false, "author_pub_id": "xf1FSRYAAAAJ:DBa1UEJaJKAC", "num_citations": 1, "citedby_url": "https://scholar.google.com/scholar?oi=bibs&hl=en&cites=8495094119472701770", "cites_id": ["8495094119472701770"]}, "xf1FSRYAAAAJ:NDuN12AVoxsC": {"container_type": "Publication", "source": "AUTHOR_PUBLICATION_ENTRY", "bib": {"title": "ExpoMotion: A Large-Scale Benchmark and A Householder Projection Network for Multi-Exposure Fusion", "pub_year": "2026", "citation": "arXiv preprint arXiv:2607.03110, 2026"}, "filled": false, "author_pub_id": "xf1FSRYAAAAJ:NDuN12AVoxsC", "num_citations": 0}, "xf1FSRYAAAAJ:6bLC7aUMtPcC": {"container_type": "Publication", "source": "AUTHOR_PUBLICATION_ENTRY", "bib": {"title": "Spread Your Wings: A Radial Strip Transformer for Image Deblurring", "pub_year": "2024", "citation": "arXiv preprint arXiv:2404.00358, 2024"}, "filled": false, "author_pub_id": "xf1FSRYAAAAJ:6bLC7aUMtPcC", "num_citations": 0}, "xf1FSRYAAAAJ:-jrNzM816MMC": {"container_type": "Publication", "source": "AUTHOR_PUBLICATION_ENTRY", "bib": {"title": "NTIRE 2026 The 3rd Restore Any Image Model (RAIM) Challenge: AI Flash Portrait (Track 3) Supplementary Material", "citation": ""}, "filled": false, "author_pub_id": "xf1FSRYAAAAJ:-jrNzM816MMC", "num_citations": 0}}, "citedby5y": 216, "hindex": 6, "hindex5y": 6, "i10index": 5, "i10index5y": 5, "cites_per_year": {"2025": 37, "2026": 178}, "updated": "2026-07-14 10:03:10.961052"}